lang2vec/__init__.py
lang2vec/lang2vec.py
lang2vec/data/family_features.npz
lang2vec/data/feature_averages.npz
lang2vec/data/feature_predictions.npz
lang2vec/data/features.npz
lang2vec/data/geocoord_features.npz
lang2vec/data/learned.npy
lang2vec/data/learned_letter_codes.json
lang2vec/data/letter_codes.json
lang2vec-1.1.2.data/scripts/lang2vec.py
lang2vec-1.1.2.dist-info/LICENSE.txt
lang2vec-1.1.2.dist-info/METADATA
lang2vec-1.1.2.dist-info/WHEEL
lang2vec-1.1.2.dist-info/top_level.txt
lang2vec-1.1.2.dist-info/zip-safe
lang2vec-1.1.2.dist-info/RECORD
