Metadata-Version: 2.1
Name: lang2vec
Version: 1.1.2
Summary: A simple library for querying the URIEL typological database.
Home-page: https://github.com/antonisa/lang2vec
Author: Patrick Littell, David Mortensen, Antonis Anastasopoulos
Author-email: aanastas@cs.cmu.com
License: UNKNOWN
Platform: UNKNOWN
Classifier: Operating System :: OS Independent
Classifier: Programming Language :: Python :: 3
Classifier: Topic :: Software Development :: Libraries :: Python Modules
Classifier: Topic :: Text Processing :: Linguistic
Requires-Dist: numpy
Requires-Dist: setuptools
